{
    "avg": {
        "wmc": 7.32,
        "ccn": 3.61,
        "bugs": 0.15,
        "kanDefect": 0.38,
        "relativeSystemComplexity": 64.91,
        "relativeDataComplexity": 1.66,
        "relativeStructuralComplexity": 63.25,
        "volume": 438.84,
        "commentWeight": 35.97,
        "intelligentContent": 57.32,
        "lcom": 1.64,
        "instability": 0.6,
        "afferentCoupling": 0.93,
        "efferentCoupling": 2.5,
        "difficulty": 6.75,
        "mi": 88.19,
        "distance": 0.41,
        "incomingCDep": 1.29,
        "incomingPDep": 0.71,
        "outgoingCDep": 3.29,
        "outgoingPDep": 2.29,
        "classesPerPackage": 4
    },
    "sum": {
        "loc": 2254,
        "cloc": 955,
        "lloc": 1308,
        "nbMethods": 132,
        "nbClasses": 28,
        "nbInterfaces": 0,
        "nbPackages": 7,
        "violations": {
            "total": 9,
            "information": 0,
            "warning": 8,
            "error": 1,
            "critical": 0
        }
    }
}