{
    "avg": {
        "wmc": 9.66,
        "ccn": 5.18,
        "bugs": 0.16,
        "kanDefect": 0.53,
        "relativeSystemComplexity": 88.58,
        "relativeDataComplexity": 1.61,
        "relativeStructuralComplexity": 86.97,
        "volume": 478.39,
        "commentWeight": 40.73,
        "intelligentContent": 56.14,
        "lcom": 1.39,
        "instability": 0.59,
        "afferentCoupling": 1.18,
        "efferentCoupling": 2.5,
        "difficulty": 7.8,
        "mi": 90.48,
        "distance": 0.45,
        "incomingCDep": 1.38,
        "incomingPDep": 0.75,
        "outgoingCDep": 3.25,
        "outgoingPDep": 2.13,
        "classesPerPackage": 4.75
    },
    "sum": {
        "loc": 3787,
        "cloc": 1750,
        "lloc": 2053,
        "nbMethods": 208,
        "nbClasses": 38,
        "nbInterfaces": 0,
        "nbPackages": 8,
        "violations": {
            "total": 13,
            "information": 1,
            "warning": 11,
            "error": 1,
            "critical": 0
        }
    }
}